{
  "units": [
    { "id": 0, "name": "UNIT_ENERGY_JOULE", "conversion_factor": 1 },
    { "id": 1, "name": "UNIT_ENERGY_CALORIE", "conversion_factor": 4.184 },
    { "id": 2, "name": "UNIT_ENERGY_KILOCALORIE", "conversion_factor": 4184 },
    {
      "id": 3,
      "name": "UNIT_ENERGY_KILOWATT_HOUR",
      "conversion_factor": 3600000
    },
    {
      "id": 4,
      "name": "UNIT_ENERGY_ELECTRONVOLT",
      "conversion_factor": 0.0000000000000000001602176634
    },
    { "id": 5, "name": "UNIT_ENERGY_BTU", "conversion_factor": 1055.05585 },
    {
      "id": 6,
      "name": "UNIT_ENERGY_FOOT_POUND",
      "conversion_factor": 1.3558179483314004
    },
    { "id": 7, "name": "UNIT_ENERGY_MEGAJOULE", "conversion_factor": 1000000 },
    {
      "id": 8,
      "name": "UNIT_ENERGY_GIGAJOULE",
      "conversion_factor": 1000000000
    },
    {
      "id": 9,
      "name": "UNIT_ENERGY_TERAWATT_HOUR",
      "conversion_factor": 3.6e12
    }
  ]
}
